mkr_format_tools/__init__.py
mkr_format_tools/_version.py
mkr_format_tools/mkr_convert_fast5.py
mkr_format_tools/mkr_inspect.py
mkr_format_tools-0.0.13.dist-info/METADATA
mkr_format_tools-0.0.13.dist-info/WHEEL
mkr_format_tools-0.0.13.dist-info/entry_points.txt
mkr_format_tools-0.0.13.dist-info/top_level.txt
mkr_format_tools-0.0.13.dist-info/RECORD
