Metadata-Version: 2.1
Name: mkr-format-tools
Version: 0.0.13
Summary: Tools for use with the MKR file format
Home-page: http://www.nanoporetech.com
Author: Oxford Nanopore Technologies plc
Author-email: support@nanoporetech.com
Keywords: nanopore
Classifier: Environment :: Console
Classifier: Intended Audience :: Developers
Classifier: Intended Audience :: Science/Research
Classifier: License :: OSI Approved :: Mozilla Public License 2.0 (MPL 2.0)
Classifier: Natural Language :: English
Classifier: Programming Language :: Python :: 3
Classifier: Topic :: Scientific/Engineering :: Bio-Informatics
Requires-Python: ~=3.7
Requires-Dist: mkr-format
Requires-Dist: h5py
